{
  "queue": {
    "pending": [
      "juliangruber/isarray",
      "jonschlinkert/is-number",
      "feross/safe-buffer",
      "mafintosh/pump",
      "substack/minimist",
      "isaacs/once",
      "isaacs/inherits",
      "tartley/colorama",
      "docopt/docopt",
      "keleshev/schema",
      "dtolnay/anyhow",
      "dtolnay/thiserror",
      "BurntSushi/ripgrep",
      "BurntSushi/xsv",
      "fatih/color",
      "sirupsen/logrus",
      "mitchellh/mapstructure"
    ],
    "in_progress": "sindresorhus/is-odd",
    "completed": [],
    "failed": []
  },
  "metadata": {
    "created_at": "2025-12-03T04:30:00.127606+00:00",
    "updated_at": "2025-12-03T04:30:07.378304+00:00",
    "category": "toy",
    "total_projects": 18
  },
  "statistics": {
    "api_calls_total": 0,
    "last_collection_duration_sec": 0.88844895362854,
    "collections_completed": 0
  }
}